LICENSE.txt
MANIFEST.in
README.md
requirements.txt
setup.py
ai_jobdeploy.egg-info/PKG-INFO
ai_jobdeploy.egg-info/SOURCES.txt
ai_jobdeploy.egg-info/dependency_links.txt
ai_jobdeploy.egg-info/entry_points.txt
ai_jobdeploy.egg-info/requires.txt
ai_jobdeploy.egg-info/top_level.txt
jd/__init__.py
jd/__main__.py
jd/controller.py
jd/resources.py
jd/templates.py
jd/utils.py
jd/values.py
jd/version.py