Metadata-Version: 2.1
Name: ai-jobdeploy
Version: 0.0.1.dev17
Summary: AI job deployment templates with YAML and Jinja2.
Home-page: https://github.com/lf1-io/jobdeploy
Author: LF1
Author-email: contact@lf1.io
License: Apache 2.0
Classifier: Programming Language :: Python :: 3.6
Classifier: Programming Language :: Python :: 3.7
Classifier: Programming Language :: Python :: 3.8
Classifier: Programming Language :: Python :: 3.9
Classifier: Topic :: Scientific/Engineering
Classifier: Topic :: Scientific/Engineering :: Artificial Intelligence
Requires-Python: >=3.6
License-File: LICENSE.txt
